civis_jupyter_notebook-2.2.1.data/scripts/civis-git-clone
civis_jupyter_notebook-2.2.1.data/scripts/civis-jupyter-notebooks-start
civis_jupyter_notebook-2.2.1.data/scripts/initialize-git
civis_jupyter_notebooks/__init__.py
civis_jupyter_notebooks/__main__.py
civis_jupyter_notebooks/git_utils.py
civis_jupyter_notebooks/notebook_config.py
civis_jupyter_notebooks/platform_persistence.py
civis_jupyter_notebooks/assets/.bashrc
civis_jupyter_notebooks/assets/civis-git-clone
civis_jupyter_notebooks/assets/civis-jupyter-notebooks-start
civis_jupyter_notebooks/assets/civis_client_config.py
civis_jupyter_notebooks/assets/custom.css
civis_jupyter_notebooks/assets/custom.js
civis_jupyter_notebooks/assets/initialize-git
civis_jupyter_notebooks/assets/ipython_config.py
civis_jupyter_notebooks/assets/jupyter_notebook_config.py
civis_jupyter_notebooks/assets/extensions/terminal.js
civis_jupyter_notebooks/assets/extensions/uncommitted_changes.js
civis_jupyter_notebooks/assets/fonts/civicons.eot
civis_jupyter_notebooks/assets/fonts/civicons.svg
civis_jupyter_notebooks/assets/fonts/civicons.ttf
civis_jupyter_notebooks/assets/fonts/civicons.woff
civis_jupyter_notebooks/assets/fonts/config.json
civis_jupyter_notebooks/extensions/__init__.py
civis_jupyter_notebooks/extensions/git/__init__.py
civis_jupyter_notebooks/extensions/git/uncommitted_changes.py
civis_jupyter_notebook-2.2.1.dist-info/LICENSE.txt
civis_jupyter_notebook-2.2.1.dist-info/METADATA
civis_jupyter_notebook-2.2.1.dist-info/WHEEL
civis_jupyter_notebook-2.2.1.dist-info/entry_points.txt
civis_jupyter_notebook-2.2.1.dist-info/top_level.txt
civis_jupyter_notebook-2.2.1.dist-info/RECORD
