Metadata-Version: 2.1
Name: civis-jupyter-notebook
Version: 2.2.1
Summary: A tool for building Docker images for Civis Platform Jupyter notebooks
Author-email: Civis Analytics <opensource@civisanalytics.com>
License: BSD-3-Clause
Project-URL: Homepage, https://www.civisanalytics.com
Project-URL: Source, https://github.com/civisanalytics/civis-jupyter-notebook
Classifier: Development Status :: 5 - Production/Stable
Classifier: License :: OSI Approved :: BSD License
Classifier: Programming Language :: Python
Classifier: Programming Language :: Python :: 3
Classifier: Programming Language :: Python :: 3 :: Only
Requires-Python: >=3.9
License-File: LICENSE.txt
Requires-Dist: civis>=2.2.0
Requires-Dist: civis-jupyter-extensions>=1.2.0
Requires-Dist: click>=6.7
Requires-Dist: GitPython>=2.1
Requires-Dist: jupyter-core>=4.6.0
Requires-Dist: notebook<7.0,>=6.4.1
Requires-Dist: requests>=2.18
Requires-Dist: tornado>=6.1.0
Provides-Extra: dev
Requires-Dist: bandit; extra == "dev"
Requires-Dist: black==24.4.2; extra == "dev"
Requires-Dist: build==1.2.1; extra == "dev"
Requires-Dist: flake8==7.0.0; extra == "dev"
Requires-Dist: pip-audit; extra == "dev"
Requires-Dist: pytest==8.2.0; extra == "dev"
Requires-Dist: twine==5.0.0; extra == "dev"
